imagelayers/__init__.py
imagelayers/main.py
imagelayers/util.py
ImageLayers-0.4.2.dist-info/METADATA
ImageLayers-0.4.2.dist-info/WHEEL
ImageLayers-0.4.2.dist-info/top_level.txt
ImageLayers-0.4.2.dist-info/RECORD
