Metadata-Version: 2.1
Name: ImageLayers
Version: 0.4.2
Summary: Split and process image segments and layers.
Home-page: https://github.com/GrandMoff100/ImageLayers
Author: GrandMoff100
Author-email: nlarsen23.student@gmail.com
License: UNKNOWN
Platform: UNKNOWN
Requires-Dist: pillow
